<PAMDataset>
  <Metadata domain="IMAGE_STRUCTURE">
    <MDI key="SOURCE_COLOR_SPACE">YCbCr</MDI>
    <MDI key="INTERLEAVE">PIXEL</MDI>
    <MDI key="COMPRESSION">JPEG</MDI>
  </Metadata>
  <PAMRasterBand band="1">
    <Metadata>
      <MDI key="STATISTICS_APPROXIMATE">YES</MDI>
      <MDI key="STATISTICS_MAXIMUM">231</MDI>
      <MDI key="STATISTICS_MEAN">133.20013427734</MDI>
      <MDI key="STATISTICS_MINIMUM">74</MDI>
      <MDI key="STATISTICS_STDDEV">29.253147324689</MDI>
      <MDI key="STATISTICS_VALID_PERCENT">100</MDI>
    </Metadata>
    <Metadata domain="IMAGE_STRUCTURE">
      <MDI key="COMPRESSION">JPEG</MDI>
    </Metadata>
  </PAMRasterBand>
  <PAMRasterBand band="2">
    <Metadata>
      <MDI key="STATISTICS_APPROXIMATE">YES</MDI>
      <MDI key="STATISTICS_MAXIMUM">199</MDI>
      <MDI key="STATISTICS_MEAN">168.83288574219</MDI>
      <MDI key="STATISTICS_MINIMUM">86</MDI>
      <MDI key="STATISTICS_STDDEV">28.965606753228</MDI>
      <MDI key="STATISTICS_VALID_PERCENT">100</MDI>
    </Metadata>
    <Metadata domain="IMAGE_STRUCTURE">
      <MDI key="COMPRESSION">JPEG</MDI>
    </Metadata>
  </PAMRasterBand>
  <PAMRasterBand band="3">
    <Metadata>
      <MDI key="STATISTICS_APPROXIMATE">YES</MDI>
      <MDI key="STATISTICS_MAXIMUM">255</MDI>
      <MDI key="STATISTICS_MEAN">221.71423339844</MDI>
      <MDI key="STATISTICS_MINIMUM">74</MDI>
      <MDI key="STATISTICS_STDDEV">51.257185591428</MDI>
      <MDI key="STATISTICS_VALID_PERCENT">100</MDI>
    </Metadata>
    <Metadata domain="IMAGE_STRUCTURE">
      <MDI key="COMPRESSION">JPEG</MDI>
    </Metadata>
  </PAMRasterBand>
</PAMDataset>
