<PAMDataset>
  <Metadata domain="IMAGE_STRUCTURE">
    <MDI key="SOURCE_COLOR_SPACE">YCbCr</MDI>
    <MDI key="INTERLEAVE">PIXEL</MDI>
    <MDI key="COMPRESSION">JPEG</MDI>
  </Metadata>
  <PAMRasterBand band="1">
    <Metadata>
      <MDI key="STATISTICS_APPROXIMATE">YES</MDI>
      <MDI key="STATISTICS_MAXIMUM">244</MDI>
      <MDI key="STATISTICS_MEAN">190.07318115234</MDI>
      <MDI key="STATISTICS_MINIMUM">91</MDI>
      <MDI key="STATISTICS_STDDEV">29.729209244645</MDI>
      <MDI key="STATISTICS_VALID_PERCENT">100</MDI>
    </Metadata>
    <Metadata domain="IMAGE_STRUCTURE">
      <MDI key="COMPRESSION">JPEG</MDI>
    </Metadata>
  </PAMRasterBand>
  <PAMRasterBand band="2">
    <Metadata>
      <MDI key="STATISTICS_APPROXIMATE">YES</MDI>
      <MDI key="STATISTICS_MAXIMUM">197</MDI>
      <MDI key="STATISTICS_MEAN">112.95959472656</MDI>
      <MDI key="STATISTICS_MINIMUM">81</MDI>
      <MDI key="STATISTICS_STDDEV">27.063340385187</MDI>
      <MDI key="STATISTICS_VALID_PERCENT">100</MDI>
    </Metadata>
    <Metadata domain="IMAGE_STRUCTURE">
      <MDI key="COMPRESSION">JPEG</MDI>
    </Metadata>
  </PAMRasterBand>
  <PAMRasterBand band="3">
    <Metadata>
      <MDI key="STATISTICS_APPROXIMATE">YES</MDI>
      <MDI key="STATISTICS_MAXIMUM">255</MDI>
      <MDI key="STATISTICS_MEAN">122.34368896484</MDI>
      <MDI key="STATISTICS_MINIMUM">71</MDI>
      <MDI key="STATISTICS_STDDEV">47.724805766131</MDI>
      <MDI key="STATISTICS_VALID_PERCENT">100</MDI>
    </Metadata>
    <Metadata domain="IMAGE_STRUCTURE">
      <MDI key="COMPRESSION">JPEG</MDI>
    </Metadata>
  </PAMRasterBand>
</PAMDataset>
